{
  "abstract_analysis": {
    "mode": "abstract",
    "total_papers": 1,
    "total_hypotheses": 9,
    "avg_hypotheses_per_paper": 9.0,
    "papers_with_hypotheses": 1,
    "papers_without_hypotheses": 0,
    "type_distributions": {
      "epistemic_type": {
        "associative": 3,
        "causal": 5,
        "descriptive": 1
      },
      "structural_type": {
        "simple": 6,
        "complex": 3
      },
      "predictive_type": {
        "non_directional": 4,
        "directional": 5
      },
      "functional_type": {
        "scientific": 9
      },
      "temporal_type": {
        "confirmatory": 8,
        "exploratory": 1
      },
      "specific_type": {
        "other": 3,
        "comparative_performance": 4,
        "transferability": 1,
        "implementation": 1
      }
    }
  },
  "pdf_analysis": {
    "mode": "pdf",
    "total_papers": 1,
    "total_hypotheses": 11,
    "avg_hypotheses_per_paper": 11.0,
    "papers_with_hypotheses": 1,
    "papers_without_hypotheses": 0,
    "type_distributions": {
      "epistemic_type": {
        "causal": 7,
        "associative": 1,
        "descriptive": 3
      },
      "structural_type": {
        "complex": 6,
        "simple": 5
      },
      "predictive_type": {
        "directional": 9,
        "non_directional": 2
      },
      "functional_type": {
        "scientific": 11
      },
      "temporal_type": {
        "confirmatory": 11
      },
      "specific_type": {
        "comparative_performance": 5,
        "other": 6
      }
    }
  },
  "per_paper_comparison": [
    {
      "paper_id": "2aKHuXdr7Q",
      "title": "Going Deeper into Locally Differentially Private Graph Neural Networks",
      "abstract_hypotheses_count": 9,
      "pdf_hypotheses_count": 11,
      "difference": 2
    }
  ],
  "matching_fractions": [
    {
      "paper_id": "2aKHuXdr7Q",
      "paper_title": "Going Deeper into Locally Differentially Private Graph Neural Networks",
      "abstract_hypotheses": 6,
      "pdf_hypotheses": 8,
      "matching_hypotheses": 3,
      "matching_fraction": 0.375
    }
  ],
  "summary": {
    "total_additional_hypotheses_in_pdf": 2,
    "avg_additional_hypotheses_per_paper": 2.0
  },
  "all_hypotheses_dataframe": [
    {
      "mode": "abstract",
      "paper_id": "2aKHuXdr7Q",
      "paper_title": "Going Deeper into Locally Differentially Private Graph Neural Networks",
      "hypothesis_index": 0,
      "epistemic_type": "associative",
      "structural_type": "simple",
      "predictive_type": "non_directional",
      "functional_type": "scientific",
      "temporal_type": "confirmatory",
      "specific_type": "other"
    },
    {
      "mode": "abstract",
      "paper_id": "2aKHuXdr7Q",
      "paper_title": "Going Deeper into Locally Differentially Private Graph Neural Networks",
      "hypothesis_index": 1,
      "epistemic_type": "associative",
      "structural_type": "simple",
      "predictive_type": "non_directional",
      "functional_type": "scientific",
      "temporal_type": "confirmatory",
      "specific_type": "other"
    },
    {
      "mode": "abstract",
      "paper_id": "2aKHuXdr7Q",
      "paper_title": "Going Deeper into Locally Differentially Private Graph Neural Networks",
      "hypothesis_index": 2,
      "epistemic_type": "causal",
      "structural_type": "simple",
      "predictive_type": "directional",
      "functional_type": "scientific",
      "temporal_type": "confirmatory",
      "specific_type": "comparative_performance"
    },
    {
      "mode": "abstract",
      "paper_id": "2aKHuXdr7Q",
      "paper_title": "Going Deeper into Locally Differentially Private Graph Neural Networks",
      "hypothesis_index": 3,
      "epistemic_type": "causal",
      "structural_type": "simple",
      "predictive_type": "directional",
      "functional_type": "scientific",
      "temporal_type": "confirmatory",
      "specific_type": "comparative_performance"
    },
    {
      "mode": "abstract",
      "paper_id": "2aKHuXdr7Q",
      "paper_title": "Going Deeper into Locally Differentially Private Graph Neural Networks",
      "hypothesis_index": 4,
      "epistemic_type": "causal",
      "structural_type": "complex",
      "predictive_type": "directional",
      "functional_type": "scientific",
      "temporal_type": "confirmatory",
      "specific_type": "comparative_performance"
    },
    {
      "mode": "abstract",
      "paper_id": "2aKHuXdr7Q",
      "paper_title": "Going Deeper into Locally Differentially Private Graph Neural Networks",
      "hypothesis_index": 5,
      "epistemic_type": "causal",
      "structural_type": "complex",
      "predictive_type": "directional",
      "functional_type": "scientific",
      "temporal_type": "confirmatory",
      "specific_type": "comparative_performance"
    },
    {
      "mode": "abstract",
      "paper_id": "2aKHuXdr7Q",
      "paper_title": "Going Deeper into Locally Differentially Private Graph Neural Networks",
      "hypothesis_index": 6,
      "epistemic_type": "associative",
      "structural_type": "simple",
      "predictive_type": "non_directional",
      "functional_type": "scientific",
      "temporal_type": "exploratory",
      "specific_type": "transferability"
    },
    {
      "mode": "abstract",
      "paper_id": "2aKHuXdr7Q",
      "paper_title": "Going Deeper into Locally Differentially Private Graph Neural Networks",
      "hypothesis_index": 7,
      "epistemic_type": "causal",
      "structural_type": "complex",
      "predictive_type": "directional",
      "functional_type": "scientific",
      "temporal_type": "confirmatory",
      "specific_type": "implementation"
    },
    {
      "mode": "abstract",
      "paper_id": "2aKHuXdr7Q",
      "paper_title": "Going Deeper into Locally Differentially Private Graph Neural Networks",
      "hypothesis_index": 8,
      "epistemic_type": "descriptive",
      "structural_type": "simple",
      "predictive_type": "non_directional",
      "functional_type": "scientific",
      "temporal_type": "confirmatory",
      "specific_type": "other"
    },
    {
      "mode": "pdf",
      "paper_id": "2aKHuXdr7Q",
      "paper_title": "Going Deeper into Locally Differentially Private Graph Neural Networks",
      "hypothesis_index": 0,
      "epistemic_type": "causal",
      "structural_type": "complex",
      "predictive_type": "directional",
      "functional_type": "scientific",
      "temporal_type": "confirmatory",
      "specific_type": "comparative_performance"
    },
    {
      "mode": "pdf",
      "paper_id": "2aKHuXdr7Q",
      "paper_title": "Going Deeper into Locally Differentially Private Graph Neural Networks",
      "hypothesis_index": 1,
      "epistemic_type": "causal",
      "structural_type": "complex",
      "predictive_type": "directional",
      "functional_type": "scientific",
      "temporal_type": "confirmatory",
      "specific_type": "comparative_performance"
    },
    {
      "mode": "pdf",
      "paper_id": "2aKHuXdr7Q",
      "paper_title": "Going Deeper into Locally Differentially Private Graph Neural Networks",
      "hypothesis_index": 2,
      "epistemic_type": "causal",
      "structural_type": "simple",
      "predictive_type": "directional",
      "functional_type": "scientific",
      "temporal_type": "confirmatory",
      "specific_type": "other"
    },
    {
      "mode": "pdf",
      "paper_id": "2aKHuXdr7Q",
      "paper_title": "Going Deeper into Locally Differentially Private Graph Neural Networks",
      "hypothesis_index": 3,
      "epistemic_type": "causal",
      "structural_type": "complex",
      "predictive_type": "directional",
      "functional_type": "scientific",
      "temporal_type": "confirmatory",
      "specific_type": "comparative_performance"
    },
    {
      "mode": "pdf",
      "paper_id": "2aKHuXdr7Q",
      "paper_title": "Going Deeper into Locally Differentially Private Graph Neural Networks",
      "hypothesis_index": 4,
      "epistemic_type": "causal",
      "structural_type": "complex",
      "predictive_type": "directional",
      "functional_type": "scientific",
      "temporal_type": "confirmatory",
      "specific_type": "other"
    },
    {
      "mode": "pdf",
      "paper_id": "2aKHuXdr7Q",
      "paper_title": "Going Deeper into Locally Differentially Private Graph Neural Networks",
      "hypothesis_index": 5,
      "epistemic_type": "causal",
      "structural_type": "simple",
      "predictive_type": "directional",
      "functional_type": "scientific",
      "temporal_type": "confirmatory",
      "specific_type": "other"
    },
    {
      "mode": "pdf",
      "paper_id": "2aKHuXdr7Q",
      "paper_title": "Going Deeper into Locally Differentially Private Graph Neural Networks",
      "hypothesis_index": 6,
      "epistemic_type": "causal",
      "structural_type": "simple",
      "predictive_type": "directional",
      "functional_type": "scientific",
      "temporal_type": "confirmatory",
      "specific_type": "comparative_performance"
    },
    {
      "mode": "pdf",
      "paper_id": "2aKHuXdr7Q",
      "paper_title": "Going Deeper into Locally Differentially Private Graph Neural Networks",
      "hypothesis_index": 7,
      "epistemic_type": "associative",
      "structural_type": "complex",
      "predictive_type": "directional",
      "functional_type": "scientific",
      "temporal_type": "confirmatory",
      "specific_type": "comparative_performance"
    },
    {
      "mode": "pdf",
      "paper_id": "2aKHuXdr7Q",
      "paper_title": "Going Deeper into Locally Differentially Private Graph Neural Networks",
      "hypothesis_index": 8,
      "epistemic_type": "descriptive",
      "structural_type": "simple",
      "predictive_type": "non_directional",
      "functional_type": "scientific",
      "temporal_type": "confirmatory",
      "specific_type": "other"
    },
    {
      "mode": "pdf",
      "paper_id": "2aKHuXdr7Q",
      "paper_title": "Going Deeper into Locally Differentially Private Graph Neural Networks",
      "hypothesis_index": 9,
      "epistemic_type": "descriptive",
      "structural_type": "complex",
      "predictive_type": "non_directional",
      "functional_type": "scientific",
      "temporal_type": "confirmatory",
      "specific_type": "other"
    },
    {
      "mode": "pdf",
      "paper_id": "2aKHuXdr7Q",
      "paper_title": "Going Deeper into Locally Differentially Private Graph Neural Networks",
      "hypothesis_index": 10,
      "epistemic_type": "descriptive",
      "structural_type": "simple",
      "predictive_type": "directional",
      "functional_type": "scientific",
      "temporal_type": "confirmatory",
      "specific_type": "other"
    }
  ]
}